u_shaped_lib-0.0.5.dist-info/METADATA
u_shaped_lib-0.0.5.dist-info/WHEEL
u_shaped_lib-0.0.5.dist-info/entry_points.txt
u_shaped_lib-0.0.5.dist-info/licenses/LICENSE
u_shaped_lib/CSH.py
u_shaped_lib/CSH_unmodified.py
u_shaped_lib/HighFinesse_FN.py
u_shaped_lib/OSA.py
u_shaped_lib/RIN.py
u_shaped_lib/__init__.py
u_shaped_lib/beatnote_drift.py
u_shaped_lib/beta_sep.py
u_shaped_lib/data_processing.py
u_shaped_lib/file_management_lib.py
u_shaped_lib/fit_functions.py
u_shaped_lib/load_data.py
u_shaped_lib/lwa_lib.py
u_shaped_lib/lwa_ushaped.py
u_shaped_lib/smsr_vs_linewidth.py
u_shaped_lib/ushaped_agilent_characterization.py
u_shaped_lib/ushaped_linewidth_vs_feedback.py
u_shaped_lib/ushaped_linewidth_vs_feedback2.py
u_shaped_lib/ushaped_smsr.py
u_shaped_lib/zeta_fit_plot.py
u_shaped_lib-0.0.5.dist-info/RECORD
