Metadata-Version: 2.1
Name: u_shaped_lib
Version: 0.0.5
Summary: A package used for dataprocessing and analysis of data obtained from the U-shaped laser
Author-Email: "Jeppe H. Surrow" <surrow@ece.au.dk>, "Simon T. Thomsen" <sthomsen@ece.au.dk>
Classifier: Programming Language :: Python :: 3
Classifier: License :: OSI Approved :: MIT License
Classifier: Operating System :: OS Independent
Project-URL: Homepage, https://github.com/auphotonicLab/PICLab-narrow-linewidth/tree/main/U_shaped_laser_package/src/u_shaped_lib
Requires-Python: >=3.8
